{
  "id": "2581923",
  "name": "WoDe",
  "font_family": "iconfont",
  "css_prefix_text": "icon-",
  "description": "",
  "glyphs": [
    {
      "icon_id": "246084",
      "name": "id",
      "font_class": "id",
      "unicode": "e67b",
      "unicode_decimal": 59003
    },
    {
      "icon_id": "1054894",
      "name": "女",
      "font_class": "icon-copy",
      "unicode": "e600",
      "unicode_decimal": 58880
    },
    {
      "icon_id": "1422724",
      "name": "右箭头",
      "font_class": "youjiantou",
      "unicode": "e612",
      "unicode_decimal": 58898
    },
    {
      "icon_id": "1903500",
      "name": "亲密付",
      "font_class": "aixinjuanzeng",
      "unicode": "e7e1",
      "unicode_decimal": 59361
    },
    {
      "icon_id": "3530623",
      "name": "用户反馈",
      "font_class": "yonghufankui",
      "unicode": "e616",
      "unicode_decimal": 58902
    },
    {
      "icon_id": "3675640",
      "name": "cd",
      "font_class": "cd",
      "unicode": "e8aa",
      "unicode_decimal": 59562
    },
    {
      "icon_id": "4315766",
      "name": "财富",
      "font_class": "caifu",
      "unicode": "e6b1",
      "unicode_decimal": 59057
    },
    {
      "icon_id": "5214419",
      "name": "背包",
      "font_class": "zhangxuyangcansaitubiao-",
      "unicode": "e60c",
      "unicode_decimal": 58892
    },
    {
      "icon_id": "6961082",
      "name": "男",
      "font_class": "nan",
      "unicode": "e601",
      "unicode_decimal": 58881
    },
    {
      "icon_id": "7804122",
      "name": "左箭头",
      "font_class": "forward",
      "unicode": "e902",
      "unicode_decimal": 59650
    },
    {
      "icon_id": "7823871",
      "name": "商 城",
      "font_class": "shangcheng",
      "unicode": "e658",
      "unicode_decimal": 58968
    },
    {
      "icon_id": "13975636",
      "name": "信用度",
      "font_class": "xinyongdu",
      "unicode": "e653",
      "unicode_decimal": 58963
    },
    {
      "icon_id": "18002297",
      "name": "男",
      "font_class": "nansheng",
      "unicode": "e609",
      "unicode_decimal": 58889
    },
    {
      "icon_id": "19260686",
      "name": "设置",
      "font_class": "shezhi",
      "unicode": "efea",
      "unicode_decimal": 61418
    },
    {
      "icon_id": "19985616",
      "name": "分 享",
      "font_class": "fenxiang",
      "unicode": "e602",
      "unicode_decimal": 58882
    }
  ]
}
